{
  "predicate": "no_hardcoded_secrets",
  "cases": [
    {
      "name": "blocks_hardcoded_aws_secret",
      "expect": "Block",
      "files": [
        {
          "path": "scripts/upload.sh",
          "text": "#!/usr/bin/env bash\nset -euo pipefail\nexport AWS_ACCESS_KEY_ID=\"AKIAIOSFODNN7EXAMPLE\"\nexport AWS_SECRET_ACCESS_KEY=\"wJalrXUtnFEMI/K7MDENG/bPxRfiCYEXAMPLEKEY\"\naws s3 cp build/ s3://artifacts/ --recursive\n"
        }
      ]
    },
    {
      "name": "allows_secrets_loaded_from_env",
      "expect": "Allow",
      "files": [
        {
          "path": "scripts/upload.sh",
          "text": "#!/usr/bin/env bash\nset -euo pipefail\n: \"${AWS_ACCESS_KEY_ID:?required}\"\n: \"${AWS_SECRET_ACCESS_KEY:?required}\"\naws s3 cp build/ s3://artifacts/ --recursive\n"
        }
      ]
    }
  ]
}
